[
{
    "model": "ontology.ontology",
    "pk": 1,
    "fields": {
        "path": "0002",
        "depth": 1,
        "numchild": 5,
        "name": "Physics",
        "description": null
    }
},
{
    "model": "ontology.ontology",
    "pk": 2,
    "fields": {
        "path": "00020004",
        "depth": 2,
        "numchild": 19,
        "name": "Mechanics",
        "description": null
    }
},
{
    "model": "ontology.ontology",
    "pk": 3,
    "fields": {
        "path": "00020004000G",
        "depth": 3,
        "numchild": 0,
        "name": "Material point method",
        "description": null
    }
},
{
    "model": "ontology.ontology",
    "pk": 4,
    "fields": {
        "path": "00020004000K",
        "depth": 3,
        "numchild": 0,
        "name": "Physical units",
        "description": null
    }
},
{
    "model": "ontology.ontology",
    "pk": 5,
    "fields": {
        "path": "000200040008",
        "depth": 3,
        "numchild": 0,
        "name": "Conservation Laws",
        "description": null
    }
},
{
    "model": "ontology.ontology",
    "pk": 6,
    "fields": {
        "path": "00020004000O",
        "depth": 3,
        "numchild": 0,
        "name": "Statics",
        "description": null
    }
},
{
    "model": "ontology.ontology",
    "pk": 7,
    "fields": {
        "path": "00020004000N",
        "depth": 3,
        "numchild": 0,
        "name": "Solid",
        "description": null
    }
},
{
    "model": "ontology.ontology",
    "pk": 8,
    "fields": {
        "path": "00020004000P",
        "depth": 3,
        "numchild": 0,
        "name": "Vector operation",
        "description": null
    }
},
{
    "model": "ontology.ontology",
    "pk": 9,
    "fields": {
        "path": "00020004000M",
        "depth": 3,
        "numchild": 0,
        "name": "Rotation",
        "description": null
    }
},
{
    "model": "ontology.ontology",
    "pk": 10,
    "fields": {
        "path": "00020004000H",
        "depth": 3,
        "numchild": 0,
        "name": "Newton's law",
        "description": null
    }
},
{
    "model": "ontology.ontology",
    "pk": 11,
    "fields": {
        "path": "000200040006",
        "depth": 3,
        "numchild": 0,
        "name": "Chocs",
        "description": null
    }
},
{
    "model": "ontology.ontology",
    "pk": 12,
    "fields": {
        "path": "00020004000L",
        "depth": 3,
        "numchild": 0,
        "name": "Relativity",
        "description": null
    }
},
{
    "model": "ontology.ontology",
    "pk": 13,
    "fields": {
        "path": "000200040009",
        "depth": 3,
        "numchild": 0,
        "name": "Fluid",
        "description": null
    }
},
{
    "model": "ontology.ontology",
    "pk": 14,
    "fields": {
        "path": "00020004000A",
        "depth": 3,
        "numchild": 0,
        "name": "Friction",
        "description": null
    }
},
{
    "model": "ontology.ontology",
    "pk": 15,
    "fields": {
        "path": "00020004000F",
        "depth": 3,
        "numchild": 0,
        "name": "Lagrange approach",
        "description": null
    }
},
{
    "model": "ontology.ontology",
    "pk": 16,
    "fields": {
        "path": "00020004000E",
        "depth": 3,
        "numchild": 0,
        "name": "Hamilton approach",
        "description": null
    }
},
{
    "model": "ontology.ontology",
    "pk": 17,
    "fields": {
        "path": "00020004000D",
        "depth": 3,
        "numchild": 0,
        "name": "Gravity",
        "description": null
    }
},
{
    "model": "ontology.ontology",
    "pk": 18,
    "fields": {
        "path": "00020004000Q",
        "depth": 3,
        "numchild": 0,
        "name": "Work, energy, power",
        "description": null
    }
},
{
    "model": "ontology.ontology",
    "pk": 19,
    "fields": {
        "path": "000200040007",
        "depth": 3,
        "numchild": 0,
        "name": "Cinematics",
        "description": null
    }
},
{
    "model": "ontology.ontology",
    "pk": 20,
    "fields": {
        "path": "00020004000J",
        "depth": 3,
        "numchild": 0,
        "name": "Period motion",
        "description": null
    }
},
{
    "model": "ontology.ontology",
    "pk": 21,
    "fields": {
        "path": "000200040005",
        "depth": 3,
        "numchild": 0,
        "name": "Angular momentum",
        "description": null
    }
},
{
    "model": "ontology.ontology",
    "pk": 22,
    "fields": {
        "path": "00020006",
        "depth": 2,
        "numchild": 11,
        "name": "Thermodynamics",
        "description": null
    }
},
{
    "model": "ontology.ontology",
    "pk": 23,
    "fields": {
        "path": "00020006000G",
        "depth": 3,
        "numchild": 0,
        "name": "Thermal equilibrium",
        "description": null
    }
},
{
    "model": "ontology.ontology",
    "pk": 24,
    "fields": {
        "path": "00020006000B",
        "depth": 3,
        "numchild": 0,
        "name": "Phase Changes",
        "description": null
    }
},
{
    "model": "ontology.ontology",
    "pk": 25,
    "fields": {
        "path": "00020006000C",
        "depth": 3,
        "numchild": 0,
        "name": "Psycometry",
        "description": null
    }
},
{
    "model": "ontology.ontology",
    "pk": 26,
    "fields": {
        "path": "00020006000E",
        "depth": 3,
        "numchild": 0,
        "name": "Statistical physics",
        "description": null
    }
},
{
    "model": "ontology.ontology",
    "pk": 27,
    "fields": {
        "path": "000200060006",
        "depth": 3,
        "numchild": 0,
        "name": "First law",
        "description": null
    }
},
{
    "model": "ontology.ontology",
    "pk": 28,
    "fields": {
        "path": "00020006000F",
        "depth": 3,
        "numchild": 0,
        "name": "Temperature",
        "description": null
    }
},
{
    "model": "ontology.ontology",
    "pk": 29,
    "fields": {
        "path": "000200060007",
        "depth": 3,
        "numchild": 0,
        "name": "Heat engines",
        "description": null
    }
},
{
    "model": "ontology.ontology",
    "pk": 30,
    "fields": {
        "path": "00020006000A",
        "depth": 3,
        "numchild": 0,
        "name": "Kinetic theory",
        "description": null
    }
},
{
    "model": "ontology.ontology",
    "pk": 31,
    "fields": {
        "path": "000200060005",
        "depth": 3,
        "numchild": 0,
        "name": "Enthalpy",
        "description": null
    }
},
{
    "model": "ontology.ontology",
    "pk": 32,
    "fields": {
        "path": "00020006000D",
        "depth": 3,
        "numchild": 0,
        "name": "Second law - Entropy",
        "description": null
    }
},
{
    "model": "ontology.ontology",
    "pk": 33,
    "fields": {
        "path": "000200060009",
        "depth": 3,
        "numchild": 0,
        "name": "Heat transfer - conduction - convection -radiation",
        "description": null
    }
},
{
    "model": "ontology.ontology",
    "pk": 34,
    "fields": {
        "path": "00020005",
        "depth": 2,
        "numchild": 6,
        "name": "Optics & light",
        "description": null
    }
},
{
    "model": "ontology.ontology",
    "pk": 35,
    "fields": {
        "path": "000200050002",
        "depth": 3,
        "numchild": 0,
        "name": "Color",
        "description": null
    }
},
{
    "model": "ontology.ontology",
    "pk": 36,
    "fields": {
        "path": "000200050006",
        "depth": 3,
        "numchild": 0,
        "name": "Intensity",
        "description": null
    }
},
{
    "model": "ontology.ontology",
    "pk": 37,
    "fields": {
        "path": "000200050009",
        "depth": 3,
        "numchild": 0,
        "name": "Propagation of light",
        "description": null
    }
},
{
    "model": "ontology.ontology",
    "pk": 38,
    "fields": {
        "path": "00020005000A",
        "depth": 3,
        "numchild": 0,
        "name": "Quantum properties",
        "description": null
    }
},
{
    "model": "ontology.ontology",
    "pk": 39,
    "fields": {
        "path": "000200050005",
        "depth": 3,
        "numchild": 0,
        "name": "Fiber optics",
        "description": null
    }
},
{
    "model": "ontology.ontology",
    "pk": 40,
    "fields": {
        "path": "000200050008",
        "depth": 3,
        "numchild": 0,
        "name": "Polarisation",
        "description": null
    }
},
{
    "model": "ontology.ontology",
    "pk": 41,
    "fields": {
        "path": "00020003",
        "depth": 2,
        "numchild": 11,
        "name": "Electromagnetism",
        "description": null
    }
},
{
    "model": "ontology.ontology",
    "pk": 42,
    "fields": {
        "path": "000200030007",
        "depth": 3,
        "numchild": 0,
        "name": "Electric circuits",
        "description": null
    }
},
{
    "model": "ontology.ontology",
    "pk": 43,
    "fields": {
        "path": "000200030005",
        "depth": 3,
        "numchild": 0,
        "name": "Circuit elements",
        "description": null
    }
},
{
    "model": "ontology.ontology",
    "pk": 44,
    "fields": {
        "path": "00020003000C",
        "depth": 3,
        "numchild": 0,
        "name": "EM waves",
        "description": null
    }
},
{
    "model": "ontology.ontology",
    "pk": 45,
    "fields": {
        "path": "00020003000B",
        "depth": 3,
        "numchild": 0,
        "name": "EMF",
        "description": null
    }
},
{
    "model": "ontology.ontology",
    "pk": 46,
    "fields": {
        "path": "000200030006",
        "depth": 3,
        "numchild": 0,
        "name": "Electric charge",
        "description": null
    }
},
{
    "model": "ontology.ontology",
    "pk": 47,
    "fields": {
        "path": "00020003000F",
        "depth": 3,
        "numchild": 0,
        "name": "Magnetic field",
        "description": null
    }
},
{
    "model": "ontology.ontology",
    "pk": 48,
    "fields": {
        "path": "00020003000A",
        "depth": 3,
        "numchild": 0,
        "name": "Electronics",
        "description": null
    }
},
{
    "model": "ontology.ontology",
    "pk": 49,
    "fields": {
        "path": "000200030004",
        "depth": 3,
        "numchild": 0,
        "name": "Bioelectricity",
        "description": null
    }
},
{
    "model": "ontology.ontology",
    "pk": 50,
    "fields": {
        "path": "000200030009",
        "depth": 3,
        "numchild": 0,
        "name": "Electric power",
        "description": null
    }
},
{
    "model": "ontology.ontology",
    "pk": 51,
    "fields": {
        "path": "00020003000E",
        "depth": 3,
        "numchild": 0,
        "name": "Lorentz force",
        "description": null
    }
},
{
    "model": "ontology.ontology",
    "pk": 52,
    "fields": {
        "path": "00020003000H",
        "depth": 3,
        "numchild": 0,
        "name": "Maxwell's equations",
        "description": null
    }
},
{
    "model": "ontology.ontology",
    "pk": 53,
    "fields": {
        "path": "00020008",
        "depth": 2,
        "numchild": 7,
        "name": "Wave & sound",
        "description": null
    }
},
{
    "model": "ontology.ontology",
    "pk": 54,
    "fields": {
        "path": "000200080002",
        "depth": 3,
        "numchild": 0,
        "name": "Hearing",
        "description": null
    }
},
{
    "model": "ontology.ontology",
    "pk": 55,
    "fields": {
        "path": "00020008000A",
        "depth": 3,
        "numchild": 0,
        "name": "Sound propagation",
        "description": null
    }
},
{
    "model": "ontology.ontology",
    "pk": 56,
    "fields": {
        "path": "000200080007",
        "depth": 3,
        "numchild": 0,
        "name": "Musical scales",
        "description": null
    }
},
{
    "model": "ontology.ontology",
    "pk": 57,
    "fields": {
        "path": "000200080009",
        "depth": 3,
        "numchild": 0,
        "name": "Sound mesurement",
        "description": null
    }
},
{
    "model": "ontology.ontology",
    "pk": 58,
    "fields": {
        "path": "000200080008",
        "depth": 3,
        "numchild": 0,
        "name": "Resonance",
        "description": null
    }
},
{
    "model": "ontology.ontology",
    "pk": 59,
    "fields": {
        "path": "00020008000C",
        "depth": 3,
        "numchild": 0,
        "name": "Travelling waves",
        "description": null
    }
},
{
    "model": "ontology.ontology",
    "pk": 60,
    "fields": {
        "path": "000200080006",
        "depth": 3,
        "numchild": 0,
        "name": "Musical instruments",
        "description": null
    }
},
{
    "model": "ontology.ontology",
    "pk": 61,
    "fields": {
        "path": "0001",
        "depth": 1,
        "numchild": 7,
        "name": "Matematics",
        "description": null
    }
},
{
    "model": "ontology.ontology",
    "pk": 62,
    "fields": {
        "path": "00010007",
        "depth": 2,
        "numchild": 6,
        "name": "Geometry",
        "description": null
    }
},
{
    "model": "ontology.ontology",
    "pk": 63,
    "fields": {
        "path": "000100070002",
        "depth": 3,
        "numchild": 0,
        "name": "Cartesian coordinate systems",
        "description": null
    }
},
{
    "model": "ontology.ontology",
    "pk": 64,
    "fields": {
        "path": "000100070006",
        "depth": 3,
        "numchild": 0,
        "name": "Cylindrical coordinate systems",
        "description": null
    }
},
{
    "model": "ontology.ontology",
    "pk": 65,
    "fields": {
        "path": "000100070007",
        "depth": 3,
        "numchild": 0,
        "name": "Spherical coordinate systems",
        "description": null
    }
},
{
    "model": "ontology.ontology",
    "pk": 66,
    "fields": {
        "path": "000100070005",
        "depth": 3,
        "numchild": 0,
        "name": "Conics",
        "description": null
    }
},
{
    "model": "ontology.ontology",
    "pk": 67,
    "fields": {
        "path": "00010007000B",
        "depth": 3,
        "numchild": 0,
        "name": "Vector analysis",
        "description": null
    }
},
{
    "model": "ontology.ontology",
    "pk": 68,
    "fields": {
        "path": "00010007000A",
        "depth": 3,
        "numchild": 0,
        "name": "Trigonometry",
        "description": null
    }
},
{
    "model": "ontology.ontology",
    "pk": 69,
    "fields": {
        "path": "00010008",
        "depth": 2,
        "numchild": 2,
        "name": "Linear algebra",
        "description": null
    }
},
{
    "model": "ontology.ontology",
    "pk": 70,
    "fields": {
        "path": "000100080004",
        "depth": 3,
        "numchild": 0,
        "name": "Matrix",
        "description": null
    }
},
{
    "model": "ontology.ontology",
    "pk": 71,
    "fields": {
        "path": "000100080003",
        "depth": 3,
        "numchild": 0,
        "name": "Determinant",
        "description": null
    }
},
{
    "model": "ontology.ontology",
    "pk": 72,
    "fields": {
        "path": "00010005",
        "depth": 2,
        "numchild": 11,
        "name": "Differential and integral calculus",
        "description": null
    }
},
{
    "model": "ontology.ontology",
    "pk": 73,
    "fields": {
        "path": "00010005000G",
        "depth": 3,
        "numchild": 0,
        "name": "Limits",
        "description": null
    }
},
{
    "model": "ontology.ontology",
    "pk": 74,
    "fields": {
        "path": "00010005000H",
        "depth": 3,
        "numchild": 0,
        "name": "Series",
        "description": null
    }
},
{
    "model": "ontology.ontology",
    "pk": 75,
    "fields": {
        "path": "000100050009",
        "depth": 3,
        "numchild": 0,
        "name": "Derivative",
        "description": null
    }
},
{
    "model": "ontology.ontology",
    "pk": 76,
    "fields": {
        "path": "000100050004",
        "depth": 3,
        "numchild": 0,
        "name": "Antiderivative  and Integral",
        "description": null
    }
},
{
    "model": "ontology.ontology",
    "pk": 77,
    "fields": {
        "path": "000100050008",
        "depth": 3,
        "numchild": 0,
        "name": "Curvilinear integrals",
        "description": null
    }
},
{
    "model": "ontology.ontology",
    "pk": 78,
    "fields": {
        "path": "00010005000I",
        "depth": 3,
        "numchild": 0,
        "name": "Taylor's theorem",
        "description": null
    }
},
{
    "model": "ontology.ontology",
    "pk": 79,
    "fields": {
        "path": "00010005000B",
        "depth": 3,
        "numchild": 0,
        "name": "Gradient",
        "description": null
    }
},
{
    "model": "ontology.ontology",
    "pk": 80,
    "fields": {
        "path": "00010005000A",
        "depth": 3,
        "numchild": 0,
        "name": "Divergence",
        "description": null
    }
},
{
    "model": "ontology.ontology",
    "pk": 81,
    "fields": {
        "path": "00010005000F",
        "depth": 3,
        "numchild": 0,
        "name": "Laplace operator",
        "description": null
    }
},
{
    "model": "ontology.ontology",
    "pk": 82,
    "fields": {
        "path": "000100050007",
        "depth": 3,
        "numchild": 0,
        "name": "Curl",
        "description": null
    }
},
{
    "model": "ontology.ontology",
    "pk": 83,
    "fields": {
        "path": "00010005000E",
        "depth": 3,
        "numchild": 0,
        "name": "Jacobian",
        "description": null
    }
},
{
    "model": "ontology.ontology",
    "pk": 84,
    "fields": {
        "path": "00010006",
        "depth": 2,
        "numchild": 6,
        "name": "Differential equations",
        "description": null
    }
},
{
    "model": "ontology.ontology",
    "pk": 85,
    "fields": {
        "path": "000100060008",
        "depth": 3,
        "numchild": 0,
        "name": "Homogeneous first order",
        "description": null
    }
},
{
    "model": "ontology.ontology",
    "pk": 86,
    "fields": {
        "path": "000100060009",
        "depth": 3,
        "numchild": 0,
        "name": "Homogeneous second-order",
        "description": null
    }
},
{
    "model": "ontology.ontology",
    "pk": 87,
    "fields": {
        "path": "000100060005",
        "depth": 3,
        "numchild": 0,
        "name": "Heterogeneous first-order",
        "description": null
    }
},
{
    "model": "ontology.ontology",
    "pk": 88,
    "fields": {
        "path": "000100060007",
        "depth": 3,
        "numchild": 0,
        "name": "Heterogeneous second-order",
        "description": null
    }
},
{
    "model": "ontology.ontology",
    "pk": 89,
    "fields": {
        "path": "00010006000A",
        "depth": 3,
        "numchild": 0,
        "name": "Partial differential equation",
        "description": null
    }
},
{
    "model": "ontology.ontology",
    "pk": 90,
    "fields": {
        "path": "000100060003",
        "depth": 3,
        "numchild": 0,
        "name": "Bessel function",
        "description": null
    }
},
{
    "model": "ontology.ontology",
    "pk": 91,
    "fields": {
        "path": "00010004",
        "depth": 2,
        "numchild": 4,
        "name": "Algebra",
        "description": null
    }
},
{
    "model": "ontology.ontology",
    "pk": 92,
    "fields": {
        "path": "000100040002",
        "depth": 3,
        "numchild": 0,
        "name": "Algebraic equation",
        "description": null
    }
},
{
    "model": "ontology.ontology",
    "pk": 93,
    "fields": {
        "path": "000100040008",
        "depth": 3,
        "numchild": 0,
        "name": "System of equations",
        "description": null
    }
},
{
    "model": "ontology.ontology",
    "pk": 94,
    "fields": {
        "path": "000100040007",
        "depth": 3,
        "numchild": 0,
        "name": "Logarithms and exponents",
        "description": null
    }
},
{
    "model": "ontology.ontology",
    "pk": 95,
    "fields": {
        "path": "000100040006",
        "depth": 3,
        "numchild": 0,
        "name": "Complex number",
        "description": null
    }
},
{
    "model": "ontology.ontology",
    "pk": 96,
    "fields": {
        "path": "0001000A",
        "depth": 2,
        "numchild": 7,
        "name": "Probability",
        "description": null
    }
},
{
    "model": "ontology.ontology",
    "pk": 97,
    "fields": {
        "path": "0001000A0007",
        "depth": 3,
        "numchild": 0,
        "name": "Combination",
        "description": null
    }
},
{
    "model": "ontology.ontology",
    "pk": 98,
    "fields": {
        "path": "0001000A0009",
        "depth": 3,
        "numchild": 0,
        "name": "Normal distribution",
        "description": null
    }
},
{
    "model": "ontology.ontology",
    "pk": 99,
    "fields": {
        "path": "0001000A000A",
        "depth": 3,
        "numchild": 0,
        "name": "Student's t-distribution",
        "description": null
    }
},
{
    "model": "ontology.ontology",
    "pk": 100,
    "fields": {
        "path": "0001000A0005",
        "depth": 3,
        "numchild": 0,
        "name": "Binomial distribution",
        "description": null
    }
},
{
    "model": "ontology.ontology",
    "pk": 101,
    "fields": {
        "path": "0001000A0006",
        "depth": 3,
        "numchild": 0,
        "name": "Chi-square distribution",
        "description": null
    }
},
{
    "model": "ontology.ontology",
    "pk": 102,
    "fields": {
        "path": "0001000A0008",
        "depth": 3,
        "numchild": 0,
        "name": "Maxwell distribution",
        "description": null
    }
},
{
    "model": "ontology.ontology",
    "pk": 103,
    "fields": {
        "path": "0001000A0004",
        "depth": 3,
        "numchild": 0,
        "name": "Bayes' theorem",
        "description": null
    }
},
{
    "model": "ontology.ontology",
    "pk": 104,
    "fields": {
        "path": "0001000C",
        "depth": 2,
        "numchild": 5,
        "name": "Statistics",
        "description": null
    }
},
{
    "model": "ontology.ontology",
    "pk": 105,
    "fields": {
        "path": "0001000C0004",
        "depth": 3,
        "numchild": 0,
        "name": "Average, variance et covariance, correlation",
        "description": null
    }
},
{
    "model": "ontology.ontology",
    "pk": 106,
    "fields": {
        "path": "0001000C0008",
        "depth": 3,
        "numchild": 0,
        "name": "Tests",
        "description": null
    }
},
{
    "model": "ontology.ontology",
    "pk": 107,
    "fields": {
        "path": "0001000C0007",
        "depth": 3,
        "numchild": 0,
        "name": "Histograms",
        "description": null
    }
},
{
    "model": "ontology.ontology",
    "pk": 108,
    "fields": {
        "path": "0001000C0003",
        "depth": 3,
        "numchild": 0,
        "name": "ANOVA",
        "description": null
    }
},
{
    "model": "ontology.ontology",
    "pk": 109,
    "fields": {
        "path": "0001000C0006",
        "depth": 3,
        "numchild": 0,
        "name": "Error calculation and confidence intervals",
        "description": null
    }
}
]
